alitra/__init__.py
alitra/alignment.py
alitra/transform.py
alitra/models/__init__.py
alitra/models/bounds.py
alitra/models/frame.py
alitra/models/map.py
alitra/models/orientation.py
alitra/models/pose.py
alitra/models/position.py
alitra/models/translation.py
alitra-1.1.5.dist-info/licenses/LICENSE
alitra-1.1.5.dist-info/METADATA
alitra-1.1.5.dist-info/WHEEL
alitra-1.1.5.dist-info/top_level.txt
alitra-1.1.5.dist-info/RECORD
